serial_interface/__about__.py
serial_interface/__init__.py
serial_interface/serial_interface.py
serial_interface-2.4.4.dist-info/LICENSE
serial_interface-2.4.4.dist-info/METADATA
serial_interface-2.4.4.dist-info/WHEEL
serial_interface-2.4.4.dist-info/top_level.txt
serial_interface-2.4.4.dist-info/RECORD
