Metadata-Version: 2.1
Name: serial-interface
Version: 2.4.4
Summary: Extends pyserial to make serial device interfaces.
Home-page: https://github.com/janelia-python/serial_interface_python
Author: Peter Polidoro
Author-email: peter@polidoro.io
License: BSD-3-Clause
Classifier: Programming Language :: Python :: 3
License-File: LICENSE
Requires-Dist: pyserial
